nfire/__init__.py
nfire/src.py
nfire-0.1.0.post6.dist-info/METADATA
nfire-0.1.0.post6.dist-info/WHEEL
nfire-0.1.0.post6.dist-info/RECORD
